relative_datetime/__init__.py
relative_datetime/datetime_utils.py
relative_datetime-0.1.4.dist-info/LICENSE
relative_datetime-0.1.4.dist-info/METADATA
relative_datetime-0.1.4.dist-info/WHEEL
relative_datetime-0.1.4.dist-info/top_level.txt
relative_datetime-0.1.4.dist-info/RECORD
