Metadata-Version: 2.1
Name: relative-datetime
Version: 0.1.4
Summary: A Python library to get relative datetime strings and parse datetime strings.
Home-page: https://github.com/mihirkhandekar/relative-datetime
Author: Mihir Khandekar
Author-email: mihirkhandekar@gmail.com
Classifier: Programming Language :: Python :: 3
Classifier: License :: OSI Approved :: MIT License
Classifier: Operating System :: OS Independent
Requires-Python: >=3.6
License-File: LICENSE
Requires-Dist: python-dateutil
Requires-Dist: pytz
